pythonatinstalib/__init__.py
pythonatinstalib/__main__.py
pythonatinstalib/config.txt
pythonatinstalib/pyinstatool.py
pythonat_instalib-1.1.0.dist-info/METADATA
pythonat_instalib-1.1.0.dist-info/WHEEL
pythonat_instalib-1.1.0.dist-info/entry_points.txt
pythonat_instalib-1.1.0.dist-info/top_level.txt
pythonat_instalib-1.1.0.dist-info/RECORD
