Metadata-Version: 2.1
Name: pythonat-instalib
Version: 1.1.0
Summary: Read the latest Real Python tutorials
Home-page: UNKNOWN
Author: Pythonat.com / dotslashhack.io
Author-email: nasser@dotslashhack.io
License: MIT
Platform: UNKNOWN
Classifier: License :: OSI Approved :: MIT License
Classifier: Programming Language :: Python :: 3
Classifier: Programming Language :: Python :: 3.7
Classifier: Programming Language :: Python :: 3.8
Classifier: Programming Language :: Python :: 3.9
Requires-Dist: os
Requires-Dist: pynput
Requires-Dist: selenium
Requires-Dist: sys
Requires-Dist: time
Requires-Dist: webdriver-manager
Requires-Dist: wget
